qxelarator/__init__.py
qxelarator/_qxelarator.cp312-win_amd64.pyd
qxelarator/qxelarator.py
qxelarator-0.10.0.dist-info/licenses/AUTHORS
qxelarator-0.10.0.dist-info/licenses/LICENSE.md
qxelarator-0.10.0.dist-info/METADATA
qxelarator-0.10.0.dist-info/WHEEL
qxelarator-0.10.0.dist-info/top_level.txt
qxelarator-0.10.0.dist-info/RECORD
