Metadata-Version: 2.4
Name: qxelarator
Version: 0.10.0
Summary: qxelarator Python Package
Home-page: https://github.com/QuTech-Delft/qx-simulator
Author: QuTech, TU Delft
Classifier: License :: OSI Approved :: Apache Software License
Classifier: Operating System :: POSIX :: Linux
Classifier: Operating System :: MacOS
Classifier: Operating System :: Microsoft :: Windows
Classifier: Programming Language :: Python :: 3 :: Only
Classifier: Programming Language :: Python :: 3.9
Classifier: Programming Language :: Python :: 3.10
Classifier: Programming Language :: Python :: 3.11
Classifier: Programming Language :: Python :: 3.12
Classifier: Programming Language :: Python :: 3.13
Classifier: Topic :: Scientific/Engineering
License-File: LICENSE.md
License-File: AUTHORS
Requires-Dist: msvc-runtime; platform_system == "Windows"
Dynamic: author
Dynamic: classifier
Dynamic: description
Dynamic: description-content-type
Dynamic: home-page
Dynamic: license-file
Dynamic: requires-dist
Dynamic: summary
